bsfs/__init__.py
bsfs/bsfs.py
bsfs/cli.py
bsfs/libbsfs.so
bsfs-0.1.2.dist-info/METADATA
bsfs-0.1.2.dist-info/WHEEL
bsfs-0.1.2.dist-info/entry_points.txt
bsfs-0.1.2.dist-info/top_level.txt
bsfs-0.1.2.dist-info/RECORD
